catface/__init__.py
catface/cli.py
catface/template/__init__.py
catface/template/cookiecutter.json
catface/template/hooks/post_gen_project.py
catface/template/hooks/pre_gen_project.py
catface/template/{{cookiecutter.project_slug}}/.dockerignore
catface/template/{{cookiecutter.project_slug}}/.gitignore
catface/template/{{cookiecutter.project_slug}}/.pre-commit-config.yaml
catface/template/{{cookiecutter.project_slug}}/.pypirc
catface/template/{{cookiecutter.project_slug}}/CHANGELOG.md
catface/template/{{cookiecutter.project_slug}}/Dockerfile
catface/template/{{cookiecutter.project_slug}}/__main__.py
catface/template/{{cookiecutter.project_slug}}/mkdocs.yml
catface/template/{{cookiecutter.project_slug}}/pip.conf
catface/template/{{cookiecutter.project_slug}}/requirements.txt
catface/template/{{cookiecutter.project_slug}}/ruff.toml
catface/template/{{cookiecutter.project_slug}}/tox.ini
catface/template/{{cookiecutter.project_slug}}/src/__init__.py
catface/template/{{cookiecutter.project_slug}}/tests/__init__.py
catface-0.1.5.dist-info/LICENSE
catface-0.1.5.dist-info/METADATA
catface-0.1.5.dist-info/WHEEL
catface-0.1.5.dist-info/entry_points.txt
catface-0.1.5.dist-info/top_level.txt
catface-0.1.5.dist-info/RECORD
