Metadata-Version: 2.1
Name: catface
Version: 0.1.5
Summary: CLI tool to setup Python projects
Author-email: Yanick andrade <yanick.jair.ta@gmail.com>
License: MIT
Project-URL: Homepage, https://github.com/YanickJair/catface
Project-URL: Repository, https://github.com/YanickJair/catface.git
Classifier: Programming Language :: Python :: 3
Classifier: License :: OSI Approved :: MIT License
Classifier: Operating System :: OS Independent
Requires-Python: >=3.11
License-File: LICENSE
Requires-Dist: click>=8.0.0
Requires-Dist: cookiecutter>=2.1.0
Requires-Dist: rich>=13.9.4
Requires-Dist: questionary>=2.0.1
Requires-Dist: pre-commit>=4.0.1
Requires-Dist: ruff>=0.8.2
